opti_query/__init__.py
opti_query/cli.py
opti_query/cli_utils/__init__.py
opti_query/cli_utils/cli_runner.py
opti_query/cli_utils/struct.py
opti_query/optipy/__init__.py
opti_query/optipy/definitions.py
opti_query/optipy/exceptions.py
opti_query/optipy/hanlder.py
opti_query/optipy/llm_clients/__init__.py
opti_query/optipy/llm_clients/base.py
opti_query/optipy/llm_clients/chatgpt.py
opti_query/optipy/llm_clients/gemini.py
opti_query/optipy/queries/__init__.py
opti_query/optipy/queries/base.py
opti_query/optipy/queries/neo4j.py
opti_query/optipy/utils/__init__.py
opti_query/optipy/utils/neo4j.py
optiquery-0.1.4.dist-info/licenses/LICENSE
optiquery-0.1.4.dist-info/METADATA
optiquery-0.1.4.dist-info/WHEEL
optiquery-0.1.4.dist-info/entry_points.txt
optiquery-0.1.4.dist-info/top_level.txt
optiquery-0.1.4.dist-info/RECORD
