Metadata-Version: 2.4
Name: optiquery
Version: 0.1.4
Summary: AI-powered database query optimization CLI
Author-email: Michael Gurevitz <gurevitz15@gmail.com>
License: MIT License
Project-URL: Homepage, https://github.com/mich-gurevitz/opti-query
Project-URL: Repository, https://github.com/mich-gurevitz/opti-query
Keywords: query,optimization,neo4j,ai,llm
Classifier: Programming Language :: Python :: 3
Classifier: License :: OSI Approved :: MIT License
Classifier: Operating System :: OS Independent
Requires-Python: >=3.8
License-File: LICENSE
Requires-Dist: pydantic
Requires-Dist: google-generativeai
Requires-Dist: neo4j
Requires-Dist: questionary
Requires-Dist: openai
Provides-Extra: dev
Requires-Dist: pre-commit; extra == "dev"
Requires-Dist: pylint; extra == "dev"
Requires-Dist: ruff; extra == "dev"
Requires-Dist: mypy; extra == "dev"
Requires-Dist: pytest; extra == "dev"
Dynamic: license-file
